validir/__init__.py
validir/cli.py
validir/template.py
validir/types.py
validir-0.1.0.dist-info/LICENSE
validir-0.1.0.dist-info/METADATA
validir-0.1.0.dist-info/WHEEL
validir-0.1.0.dist-info/entry_points.txt
validir-0.1.0.dist-info/top_level.txt
validir-0.1.0.dist-info/RECORD
