Metadata-Version: 2.1
Name: validir
Version: 0.1.0
Summary: Directory structure template-based validation.
Author-email: "Daniel M. Sahu" <danielmohansahu@gmail.com>
Project-URL: Homepage, https://github.com/danielmohansahu/validir
Project-URL: Bug Tracker, https://github.com/danielmohansahu/validir/issues
Classifier: Programming Language :: Python :: 3
Classifier: License :: OSI Approved :: MIT License
Classifier: Operating System :: OS Independent
Requires-Python: >=3.7
License-File: LICENSE
Requires-Dist: pyyaml
